repana/__init__.py
repana/controlModel.py
repana/controlVector.py
repana/utils.py
repana-0.0.4.dist-info/METADATA
repana-0.0.4.dist-info/WHEEL
repana-0.0.4.dist-info/licenses/LICENSE
repana-0.0.4.dist-info/RECORD
