Metadata-Version: 2.4
Name: repana
Version: 0.0.4
Dynamic: Requires-Dist
Summary: A simple framework for analyzing model representations
Author: Bertram Højer
License: Copyright (c) 2025 Bertram Højer
License-File: LICENSE
Classifier: License :: OSI Approved :: MIT License
Classifier: Operating System :: OS Independent
Classifier: Programming Language :: Python :: 3
Requires-Python: >=3.10
